unipipe/__init__.py
unipipe/cli.py
unipipe/dsl.py
unipipe/backend/__init__.py
unipipe/backend/kfp.py
unipipe/executor/__init__.py
unipipe/executor/base.py
unipipe/executor/docker.py
unipipe/executor/python.py
unipipe/executor/vertex.py
unipipe/utils/__init__.py
unipipe/utils/annotations.py
unipipe/utils/compat.py
unipipe/utils/ops.py
unipipe/utils/scripts.py
unipipe-0.5.4.dist-info/LICENSE
unipipe-0.5.4.dist-info/METADATA
unipipe-0.5.4.dist-info/WHEEL
unipipe-0.5.4.dist-info/entry_points.txt
unipipe-0.5.4.dist-info/top_level.txt
unipipe-0.5.4.dist-info/RECORD
