Metadata-Version: 2.1
Name: unipipe
Version: 0.5.4
Summary: project_description
Home-page: https://github.com/fkodom/unipipe
Author: Frank Odom
Author-email: frank.odom.iii@gmail.com
Classifier: Programming Language :: Python :: 3
Classifier: Operating System :: OS Independent
Requires-Python: >=3.7
License-File: LICENSE
Requires-Dist: click
Requires-Dist: pydantic
Requires-Dist: typing-extensions
Provides-Extra: all
Requires-Dist: docker (>=5.0) ; extra == 'all'
Requires-Dist: kfp (>=1.8) ; extra == 'all'
Requires-Dist: google-cloud-aiplatform (>=1.10) ; extra == 'all'
Requires-Dist: arrow (>=1.2) ; extra == 'all'
Requires-Dist: black (>=22.6) ; extra == 'all'
Requires-Dist: flake8 (>=5.0) ; extra == 'all'
Requires-Dist: isort (>=5.10) ; extra == 'all'
Requires-Dist: mypy (>=0.971) ; extra == 'all'
Requires-Dist: pytest (>=7.1) ; extra == 'all'
Requires-Dist: pytest-cov (>=3.0) ; extra == 'all'
Requires-Dist: torch (>=1.8) ; extra == 'all'
Requires-Dist: torchvision (>=0.9) ; extra == 'all'
Requires-Dist: pre-commit (>=2.20) ; extra == 'all'
Provides-Extra: dev
Requires-Dist: pre-commit (>=2.20) ; extra == 'dev'
Requires-Dist: arrow (>=1.2) ; extra == 'dev'
Requires-Dist: black (>=22.6) ; extra == 'dev'
Requires-Dist: flake8 (>=5.0) ; extra == 'dev'
Requires-Dist: isort (>=5.10) ; extra == 'dev'
Requires-Dist: mypy (>=0.971) ; extra == 'dev'
Requires-Dist: pytest (>=7.1) ; extra == 'dev'
Requires-Dist: pytest-cov (>=3.0) ; extra == 'dev'
Requires-Dist: torch (>=1.8) ; extra == 'dev'
Requires-Dist: torchvision (>=0.9) ; extra == 'dev'
Provides-Extra: docker
Requires-Dist: docker (>=5.0) ; extra == 'docker'
Provides-Extra: test
Requires-Dist: arrow (>=1.2) ; extra == 'test'
Requires-Dist: black (>=22.6) ; extra == 'test'
Requires-Dist: flake8 (>=5.0) ; extra == 'test'
Requires-Dist: isort (>=5.10) ; extra == 'test'
Requires-Dist: mypy (>=0.971) ; extra == 'test'
Requires-Dist: pytest (>=7.1) ; extra == 'test'
Requires-Dist: pytest-cov (>=3.0) ; extra == 'test'
Requires-Dist: torch (>=1.8) ; extra == 'test'
Requires-Dist: torchvision (>=0.9) ; extra == 'test'
Provides-Extra: vertex
Requires-Dist: kfp (>=1.8) ; extra == 'vertex'
Requires-Dist: google-cloud-aiplatform (>=1.10) ; extra == 'vertex'
